code_run_dt/__init__.py
code_run_dt/auth.py
code_run_dt/job.py
code_run_dt/report/__init__.py
code_run_dt/task.py
code_run_dt/task_config/__init__.py
code_run_dt/task_config/c_task.py
code_run_dt/task_config/js_task.py
code_run_dt/task_config/php_task.py
code_run_dt/task_config/py_task.py
code_run_dt/task_config/rust_task.py
code_run_dt/task_config/shared.py
code_run_dt/test_auth.py
code_run_dt-0.4.0.dist-info/WHEEL
code_run_dt-0.4.0.dist-info/METADATA
code_run_dt-0.4.0.dist-info/RECORD
