Metadata-Version: 2.1
Name: code-run-dt
Version: 0.4.0
Summary: 编程乐园类型定义
Home-page: https://run.c-art.tech/
Author: dev
Author-email: dev@qiyutech.tech
Requires-Python: >=3.9,<4.0
Classifier: Programming Language :: Python :: 3
Classifier: Programming Language :: Python :: 3.9
Requires-Dist: pydantic (>=1.7,<2.0)
